IpfsYiwenyida/README.md
IpfsYiwenyida/__init__.py
IpfsYiwenyida/__main__.py
IpfsYiwenyida/file.epub
IpfsYiwenyida/index.html
IpfsYiwenyida/css/__init__.py
IpfsYiwenyida/css/annotations.css
IpfsYiwenyida/css/main.css
IpfsYiwenyida/css/normalize.css
IpfsYiwenyida/css/popup.css
IpfsYiwenyida/font/__init__.py
IpfsYiwenyida/font/fontello.eot
IpfsYiwenyida/font/fontello.svg
IpfsYiwenyida/font/fontello.ttf
IpfsYiwenyida/font/fontello.woff
IpfsYiwenyida/img/__init__.py
IpfsYiwenyida/img/annotator-glyph-sprite.png
IpfsYiwenyida/img/annotator-icon-sprite.png
IpfsYiwenyida/img/apple-touch-icon.png
IpfsYiwenyida/img/cancelfullscreen.png
IpfsYiwenyida/img/close.png
IpfsYiwenyida/img/fullscreen.png
IpfsYiwenyida/img/loader.gif
IpfsYiwenyida/img/menu-icon.png
IpfsYiwenyida/img/save.png
IpfsYiwenyida/img/saved.png
IpfsYiwenyida/img/settings-s.png
IpfsYiwenyida/img/settings.png
IpfsYiwenyida/img/star.png
IpfsYiwenyida/js/__init__.py
IpfsYiwenyida/js/epub.js
IpfsYiwenyida/js/epub.min.js
IpfsYiwenyida/js/epub.min.map
IpfsYiwenyida/js/hooks.min.js
IpfsYiwenyida/js/hooks.min.map
IpfsYiwenyida/js/reader.js
IpfsYiwenyida/js/reader.js.map
IpfsYiwenyida/js/reader.min.js
IpfsYiwenyida/js/reader.min.map
IpfsYiwenyida/js/hooks/__init__.py
IpfsYiwenyida/js/hooks/extensions/__init__.py
IpfsYiwenyida/js/hooks/extensions/highlight.js
IpfsYiwenyida/js/libs/__init__.py
IpfsYiwenyida/js/libs/jquery.min.js
IpfsYiwenyida/js/libs/localforage.min.js
IpfsYiwenyida/js/libs/screenfull.js
IpfsYiwenyida/js/libs/screenfull.min.js
IpfsYiwenyida/js/libs/zip.min.js
IpfsYiwenyida/js/plugins/__init__.py
IpfsYiwenyida/js/plugins/hypothesis.js
IpfsYiwenyida/js/plugins/search.js
ipfs_yiwenyida-2024.3.4.0.dist-info/METADATA
ipfs_yiwenyida-2024.3.4.0.dist-info/WHEEL
ipfs_yiwenyida-2024.3.4.0.dist-info/entry_points.txt
ipfs_yiwenyida-2024.3.4.0.dist-info/top_level.txt
ipfs_yiwenyida-2024.3.4.0.dist-info/RECORD
